ovos_messagebus/__init__.py
ovos_messagebus/__main__.py
ovos_messagebus/event_handler.py
ovos_messagebus/load_config.py
ovos_messagebus/version.py
ovos_messagebus-0.0.10.dist-info/LICENSE.md
ovos_messagebus-0.0.10.dist-info/METADATA
ovos_messagebus-0.0.10.dist-info/WHEEL
ovos_messagebus-0.0.10.dist-info/entry_points.txt
ovos_messagebus-0.0.10.dist-info/top_level.txt
ovos_messagebus-0.0.10.dist-info/RECORD
