Metadata-Version: 2.1
Name: ovos-messagebus
Version: 0.0.10
Summary: ovos-core reference python bus daemon
Home-page: https://github.com/OpenVoiceOS/ovos-messagebus
License: Apache-2.0
Classifier: Development Status :: 4 - Beta
Classifier: Programming Language :: Python :: 3
Classifier: License :: OSI Approved :: Apache Software License
License-File: LICENSE.md
Requires-Dist: tornado>=6.0.3,~=6.0
Requires-Dist: ovos-bus-client<2.0.0,>=0.0.7
Requires-Dist: ovos-utils<1.0.0,>=0.0.37
Requires-Dist: ovos-config<2.0.0,>=0.0.12
